lloam/__init__.py
lloam/agent.py
lloam/completions.py
lloam/prompt.py
lloam/streaming.py
lloam/utils.py
lloam-0.1.3.dist-info/METADATA
lloam-0.1.3.dist-info/WHEEL
lloam-0.1.3.dist-info/top_level.txt
lloam-0.1.3.dist-info/RECORD
