Metadata-Version: 2.1
Name: lloam
Version: 0.1.3
Summary: A fertile collection of primitives for building things with LLMs
Home-page: https://github.com/LachlanGray/lloam
Author: Lachlan Gray
Requires-Dist: openai >=1.51.0
